quart_trio/__init__.py
quart_trio/app.py
quart_trio/asgi.py
quart_trio/py.typed
quart_trio/request.py
quart_trio/response.py
quart_trio/testing.py
quart_trio/utils.py
Quart_Trio_Twice-0.6.1.dist-info/LICENSE
Quart_Trio_Twice-0.6.1.dist-info/METADATA
Quart_Trio_Twice-0.6.1.dist-info/WHEEL
Quart_Trio_Twice-0.6.1.dist-info/top_level.txt
Quart_Trio_Twice-0.6.1.dist-info/RECORD
