Metadata-Version: 2.1
Name: Quart-Trio-Twice
Version: 0.6.1
Summary: Quart-Trio 0.6 temporary fork
Home-page: https://gitlab.com/pgjones/quart-trio/
Author: P G Jones
Author-email: philip.graham.jones@googlemail.com
License: MIT
Platform: UNKNOWN
Classifier: Development Status :: 3 - Alpha
Classifier: Environment :: Web Environment
Classifier: Intended Audience :: Developers
Classifier: License :: OSI Approved :: MIT License
Classifier: Operating System :: OS Independent
Classifier: Programming Language :: Python
Classifier: Programming Language :: Python :: 3
Classifier: Programming Language :: Python :: 3.7
Classifier: Programming Language :: Python :: 3.8
Classifier: Topic :: Internet :: WWW/HTTP :: Dynamic Content
Classifier: Topic :: Software Development :: Libraries :: Python Modules
Requires-Python: >=3.7.0
Requires-Dist: hypercorn[trio] (>=0.6.0)
Requires-Dist: quart (<0.14,>=0.12)
Requires-Dist: trio (>=0.9.0)
